scalelite/__init__.py
scalelite/__main__.py
scalelite/scalelite.py
scalelite-0.1.4.dist-info/LICENSE
scalelite-0.1.4.dist-info/METADATA
scalelite-0.1.4.dist-info/WHEEL
scalelite-0.1.4.dist-info/top_level.txt
scalelite-0.1.4.dist-info/RECORD
